jwt4auth/aiohttp.py
jwt4auth/general.py
jwt4auth-0.1.5.dist-info/LICENSE
jwt4auth-0.1.5.dist-info/METADATA
jwt4auth-0.1.5.dist-info/WHEEL
jwt4auth-0.1.5.dist-info/top_level.txt
jwt4auth-0.1.5.dist-info/RECORD
