Metadata-Version: 2.1
Name: jwt4auth
Version: 0.1.5
Summary: UNKNOWN
Home-page: https://github.com/alesh/jwt4auth
Author: Alexey Poryadin
Author-email: alexey.poryadin@gmail.com
License: http://opensource.org/licenses/LGPL-3.0
Keywords: jwt access refresh token auth authentication authorization aiohttp react typescript javascript
Platform: UNKNOWN
Classifier: Framework :: AsyncIO
Classifier: Intended Audience :: Developers
Classifier: License :: OSI Approved :: GNU General Public License v3 or later (GPLv3+)
Classifier: Programming Language :: Python :: 3
Requires-Dist: aiohttp (==3.7.2)
Requires-Dist: PyJWT (==1.7.1)
